xmonkey_namonica/__init__.py
xmonkey_namonica/cli.py
xmonkey_namonica/common.py
xmonkey_namonica/utils.py
xmonkey_namonica/handlers/__init__.py
xmonkey_namonica/handlers/base_handler.py
xmonkey_namonica/handlers/cargo_handler.py
xmonkey_namonica/handlers/conda_handler.py
xmonkey_namonica/handlers/gem_handler.py
xmonkey_namonica/handlers/gen_handler.py
xmonkey_namonica/handlers/github_handler.py
xmonkey_namonica/handlers/golang_handler.py
xmonkey_namonica/handlers/npm_handler.py
xmonkey_namonica/handlers/nuget_handler.py
xmonkey_namonica/handlers/pypi_handler.py
xmonkey_namonica-0.1.41.dist-info/LICENSE
xmonkey_namonica-0.1.41.dist-info/METADATA
xmonkey_namonica-0.1.41.dist-info/WHEEL
xmonkey_namonica-0.1.41.dist-info/entry_points.txt
xmonkey_namonica-0.1.41.dist-info/top_level.txt
xmonkey_namonica-0.1.41.dist-info/RECORD
